pulpo_config/__init__.py
pulpo_config/pulpo_config.py
pulpo_config-2.0.2.dist-info/LICENSE
pulpo_config-2.0.2.dist-info/METADATA
pulpo_config-2.0.2.dist-info/WHEEL
pulpo_config-2.0.2.dist-info/top_level.txt
pulpo_config-2.0.2.dist-info/RECORD
