Metadata-Version: 2.1
Name: pulpo-config
Version: 2.0.2
Summary: Simple configuration library
Author: Mighty Pulpo
Author-email: jayray.net@gmail.com
Keywords: configuration
Classifier: Programming Language :: Python :: 3
Classifier: License :: OSI Approved :: MIT License
Classifier: Operating System :: OS Independent
Requires-Python: >=3.6
License-File: LICENSE
Requires-Dist: pyyaml ==6.0.1
